epickledb_tedd28014/__init__.py
epickledb_tedd28014/epickledb.py
epickledb-1.0.1.dist-info/LICENSE
epickledb-1.0.1.dist-info/METADATA
epickledb-1.0.1.dist-info/WHEEL
epickledb-1.0.1.dist-info/top_level.txt
epickledb-1.0.1.dist-info/RECORD
