Metadata-Version: 2.1
Name: epickledb
Version: 1.0.1
Summary: An enhanced distribution of PickleDB
Author: Tedd Saito
License: BSD License
License-File: LICENSE
Requires-Dist: Thread
